ECSEval/__init__.py
ECSEval/summary_evaluator.py
ECSEval-0.0.3.dist-info/METADATA
ECSEval-0.0.3.dist-info/WHEEL
ECSEval-0.0.3.dist-info/top_level.txt
ECSEval-0.0.3.dist-info/RECORD
