Metadata-Version: 2.1
Name: ECSEval
Version: 0.0.3
Summary: Evaluating environmental contamination summaries
Home-page: https://github.com/dreji18/ECSEval
Author: Deepak John Reji, Afreen Aman
Author-email: afreenaman90@gmail.com
License: MIT
Classifier: License :: OSI Approved :: MIT License
Classifier: Programming Language :: Python :: 3.8
Classifier: Programming Language :: Python :: 3.10
Classifier: Programming Language :: Python :: 3.11
Classifier: Programming Language :: Python :: 3.12
Requires-Dist: nltk
Requires-Dist: scikit-learn==1.5.1
Requires-Dist: langchain==0.3.14
